{"cameraMode":{"drawMode":0,"name":"Shaded","section":"Shading Mode"},"sceneLighting":true,"audioPlay":false,"sceneViewState":{"m_AlwaysRefresh":false,"showFog":true,"showSkybox":true,"showFlares":true,"showImageEffects":true,"showParticleSystems":true,"showVisualEffectGraphs":true,"m_FxEnabled":true},"in2DMode":false,"pivot":{"x":-991.8275146484375,"y":19.974233627319337,"z":-411.32440185546877},"rotation":{"x":0.17045001685619355,"y":0.37744665145874026,"z":-0.07184627652168274,"w":0.9075663685798645},"size":12.12435531616211,"orthographic":false}